binarystream/__init__.py
binarystream/binary_stream.py
binarystream/read_only_binary_stream.py
mcbe_binarystream-2.1.0.dist-info/licenses/LICENSE
mcbe_binarystream-2.1.0.dist-info/METADATA
mcbe_binarystream-2.1.0.dist-info/WHEEL
mcbe_binarystream-2.1.0.dist-info/top_level.txt
mcbe_binarystream-2.1.0.dist-info/RECORD
