Metadata-Version: 2.4
Name: mcbe-binarystream
Version: 2.1.0
Summary: Minecraft BinaryStream Library written in Python
Home-page: https://github.com/GlacieTeam/BinaryStream-Python
Author: GlacieTeam
License: MPL-2.0
Classifier: Programming Language :: Python :: 3
Classifier: License :: OSI Approved :: Mozilla Public License 2.0 (MPL 2.0)
Classifier: Operating System :: OS Independent
Requires-Python: >=3
License-File: LICENSE
Dynamic: author
Dynamic: classifier
Dynamic: description
Dynamic: description-content-type
Dynamic: home-page
Dynamic: license
Dynamic: license-file
Dynamic: requires-python
Dynamic: summary
